framadatectl/__about__.py
framadatectl/__init__.py
framadatectl/__main__.py
framadatectl/commands.py
framadatectl/configuration.py
framadatectl/framadate.py
framadatectl/slot.py
framadatectl/vote.py
framadatectl-0.3.0.dist-info/LICENSE.md
framadatectl-0.3.0.dist-info/METADATA
framadatectl-0.3.0.dist-info/WHEEL
framadatectl-0.3.0.dist-info/entry_points.txt
framadatectl-0.3.0.dist-info/top_level.txt
framadatectl-0.3.0.dist-info/RECORD
