Metadata-Version: 2.1
Name: framadatectl
Version: 0.3.0
Summary: A tool to manage a Framadate
Home-page: https://gitlab.com/albinou/python-framadatectl
Author: Albin Kauffmann
Author-email: albin@kauff.org
License: UNKNOWN
Project-URL: Bug Reports, https://gitlab.com/albinou/python-framadatectl/issues
Project-URL: Source, https://gitlab.com/albinou/python-framadatectl
Keywords: framadate framasoft
Platform: UNKNOWN
Classifier: Development Status :: 4 - Beta
Classifier: Intended Audience :: End Users/Desktop
Classifier: Topic :: Games/Entertainment
Classifier: License :: OSI Approved :: GNU General Public License v3 or later (GPLv3+)
Classifier: Programming Language :: Python :: 3.7
Classifier: Programming Language :: Python :: 3.8
Classifier: Programming Language :: Python :: 3 :: Only
Requires-Python: >=3.7, <4
License-File: LICENSE.md
Requires-Dist: bs4
Requires-Dist: pyyaml
Requires-Dist: requests
